llmtraceviewer/__init__.py
llmtraceviewer/cli.py
llmtraceviewer/server.py
llmtraceviewer/_frontend_out/404.html
llmtraceviewer/_frontend_out/index.html
llmtraceviewer/_frontend_out/index.txt
llmtraceviewer/_frontend_out/_next/static/LSJKJtFpRNyjQiXDp5MSd/_buildManifest.js
llmtraceviewer/_frontend_out/_next/static/LSJKJtFpRNyjQiXDp5MSd/_ssgManifest.js
llmtraceviewer/_frontend_out/_next/static/chunks/0e5ce63c-6c742338cee2e1cf.js
llmtraceviewer/_frontend_out/_next/static/chunks/4bd1b696-0373c3b5d086cc82.js
llmtraceviewer/_frontend_out/_next/static/chunks/684-4eeab784e518347e.js
llmtraceviewer/_frontend_out/_next/static/chunks/framework-f593a28cde54158e.js
llmtraceviewer/_frontend_out/_next/static/chunks/main-app-bf9ea4edff00f3e6.js
llmtraceviewer/_frontend_out/_next/static/chunks/main-b66362da7e9066c6.js
llmtraceviewer/_frontend_out/_next/static/chunks/polyfills-42372ed130431b0a.js
llmtraceviewer/_frontend_out/_next/static/chunks/webpack-60d835819e29e072.js
llmtraceviewer/_frontend_out/_next/static/chunks/app/layout-d238e1155c3539ee.js
llmtraceviewer/_frontend_out/_next/static/chunks/app/page-46f080001412ea2a.js
llmtraceviewer/_frontend_out/_next/static/chunks/app/_not-found/page-c4834b17169c85e0.js
llmtraceviewer/_frontend_out/_next/static/chunks/pages/_app-da15c11dea942c36.js
llmtraceviewer/_frontend_out/_next/static/chunks/pages/_error-cc3f077a18ea1793.js
llmtraceviewer/_frontend_out/_next/static/css/698f43700c461742.css
llmtraceviewer-0.2.0.dist-info/licenses/LICENSE
llmtraceviewer-0.2.0.dist-info/METADATA
llmtraceviewer-0.2.0.dist-info/WHEEL
llmtraceviewer-0.2.0.dist-info/entry_points.txt
llmtraceviewer-0.2.0.dist-info/top_level.txt
llmtraceviewer-0.2.0.dist-info/RECORD
