Metadata-Version: 2.4
Name: llmtraceviewer
Version: 0.2.0
Summary: A tool to view LLM call traces from JSONL log files.
Author-email: Your Name <your.email@example.com>
Requires-Python: >=3.8
License-File: LICENSE
Requires-Dist: fastapi
Requires-Dist: uvicorn
Dynamic: license-file
